MANIFEST.in
requirements.txt
setup.cfg
setup.py
hestia/__init__.py
hestia/_version.py
hestia/api.py
hestia_api.egg-info/PKG-INFO
hestia_api.egg-info/SOURCES.txt
hestia_api.egg-info/dependency_links.txt
hestia_api.egg-info/requires.txt
hestia_api.egg-info/top_level.txt