Metadata-Version: 1.1
Name: hestia-api
Version: 0.0.8
Summary: Python library for accessing the hestia.io API
Home-page: https://www.hestia.io
Author: hestia.io
Author-email: info@hestia.io
License: UNKNOWN
Download-URL: https://github.com/hestiaio/hestia-python-api/tarball/0.0.1
Platform: UNKNOWN
